rtl/ALERT_COUNTER.v
module ALERT_COUNTER(/*AUTOARG*/
   // Outputs
   ALERT, ALERT_OFF,
   // Inputs
   ENABLE, CLK
   );
   input ENABLE, CLK;
   output reg ALERT, ALERT_OFF;

   reg [2:0]  CNT;

   always @ (posedge CLK)
     begin
	if(ENABLE == 1)
	  begin
	     if(CNT == 5)
	       begin
		  CNT <= 0;
		  ALERT <= 0;
		  ALERT_OFF <= 1;
	       end

	     else if((ENABLE == 1) && (ALERT_OFF == 1))
	       begin
		  CNT <= 0;
		  ALERT <= 0;
		  ALERT_OFF <= 1;
	       end
	     
	     else
	       begin
		  CNT <= CNT + 1;
		  ALERT <= 1;
	       end // else: !if(CNT == 5)
	  end // if (ENABLE == 1)
	     
	else
	  begin
	     CNT <= 0;
	     ALERT <= 0;
	     ALERT_OFF <= 0;
	  end // else: !if(ENABLE)
     end // always @ (posedge CLK)
endmodule // ALERT_COUNTER

rtl/PW_RESET.v
module PW_RESET(/*AUTOARG*/
   // Outputs
   PW, PW_TEMP,
   // Inputs
   CLK, CORRECT, PW_TEMP_RESET, HASH, STAR, RESET, DISPLAY
   );
   input			CLK, CORRECT, PW_TEMP_RESET, HASH, STAR, RESET; //HASH=#, STAR=*, RESET
   input [15:0]			DISPLAY;
   output reg [15:0]		PW, PW_TEMP;
   parameter			INIT = 0;
   parameter			PAR_PW = 1;
   parameter			PAR_PW_TEMP = 2;
   
   reg [2:0]			STATE;
   
   always @(posedge CLK) begin
      if(RESET) begin
	 PW = 0;
	 PW_TEMP <= 16'bz;
	 STATE = 0;
      end
      else if (PW_TEMP_RESET) PW_TEMP <= 16'bz;
      
      else begin
	 case(STATE)
	   INIT: begin
	      if(CORRECT && STAR)
		begin
		   STATE = PW;
		end
	      else if (CORRECT && HASH)
		begin
		   STATE = PAR_PW_TEMP;
		end
	      else STATE = INIT;
	   end
	   
	   PW: begin
	      PW <= DISPLAY;
	      if(STAR) begin
		 STATE = INIT;
	      end
	      else STATE = PAR_PW;
	   end // case: PW
	   
	   PW_TEMP: begin
	      PW_TEMP <= DISPLAY;
	      if(HASH) begin
		 STATE = INIT;
	      end
	      else STATE = PAR_PW_TEMP;
	   end // case: PW_TEMP
	   
	 endcase // case (STATE)
      end // else: !if(PW_TEMP_RESET)
   end // always @ (posedge CLK)
endmodule // PW_RESET

DDL_Project1/rtl/COMPARE.v
module COMPARE(/*AUTOARG*/
   // Outputs
   CORRECT, ALERT, PW_TEMP_RESET,
   // Inputs
   STAR, CLK, ALERT_OFF, CLOSE_SENSOR, PW, PW_TEMP, DISPLAY
   );
   input       STAR, CLK, ALERT_OFF,CLOSE_SENSOR;
   input [15:0]	PW, PW_TEMP, DISPLAY;
   output	CORRECT, ALERT, PW_TEMP_RESET;
   integer	WRONG = 0;
   
   reg			ALERT, CORRECT, PW_TEMP_RESET, UNLOCK;

   always@ (posedge CLK)
     begin
	if (STAR) // '*'button press
	  begin
	     if(DISPLAY == PW)
	       begin
		  CORRECT <= 1;
		  WRONG <= 0;
	       end
	     else if(DISPLAY == PW_TEMP)
	       begin
		  CORRECT <= 1;
		  WRONG <= 0;
		  PW_TEMP_RESET <= 1; //temp password reset
	       end
	     else if(CORRECT == 0)
	       begin
		  if ((DISPLAY != PW) || (DISPLAY != PW_TEMP))
		    begin
		       WRONG = WRONG + 1;
		       if(WRONG == 5)
			 begin
			    ALERT <= 1;
			    WRONG <= 0;
			 end
		    end
	       end // if (UNLOCK == 0)
	  end // if (STAR)
	
	else
	  begin
	     if (ALERT_OFF == 1)
	       ALERT <= 0;
	     else if (CLOSE_SENSOR == 1)
	       begin
		  CORRECT <= 0;
		  PW_TEMP_RESET <= 0;
	       end
	  end // else: !if(STAR)
     end // always@ (posedge CLK)
endmodule // COMPARE

rtl/RANDOM_NUMBERS.v
module RANDOM_NUMBERS(/*AUTOARG*/
   // Outputs
   O_NUM,
   // Inputs
   I_NUM, STAR
   );
   input [9:0] I_NUM;
   input       STAR;
   output [9:0]	O_NUM;

   integer	a;
   wire [9:0]	MID_NUM;

   assign MID_NUM = {I_NUM[1],I_NUM[3],I_NUM[7],I_NUM[9],I_NUM[2],I_NUM[0],I_NUM[8],I_NUM[5],I_NUM[6],I_NUM[4]};
   assign O_NUM = (MID_NUM << a | MID_NUM >> (10-a));

   always @(posedge STAR) begin
         a <= $urandom_range(0, 9);
   end
endmodule // RANDOM_NUMBERS

rtl/DISPLAY.v
module DISPLAY(/*AUTOARG*/
   // Outputs
   DISPLAY,
   // Inputs
   BUTTON, STAR, HASH, CLK
   );
   input [9:0] BUTTON;
   input       STAR, HASH;
   input       CLK;
   output reg [15:0] DISPLAY;
   
   always@ (posedge CLK)
     begin
	
   if (STAR | HASH) // *(reset), #
     begin
	DISPLAY <= 16'd0;
     end
	
   else
     begin
	if (BUTTON[0])
	  begin
	     DISPLAY <= DISPLAY * 10 + 0;
	  end
	else if (BUTTON[1])
	  begin
	     DISPLAY <= DISPLAY * 10 + 1;
	  end
	else if (BUTTON[2])
	  begin
	     DISPLAY <= DISPLAY * 10 + 2;
	  end
	else if (BUTTON[3])
	  begin
	     DISPLAY <= DISPLAY * 10 + 3;
	  end
	else if (BUTTON[4])
	  begin
	     DISPLAY <= DISPLAY * 10 + 4;
	  end
	else if (BUTTON[5])
	  begin
	     DISPLAY <= DISPLAY * 10 + 5;
	  end
	else if (BUTTON[6])
	  begin
	     DISPLAY <= DISPLAY * 10 + 6;
	  end
	else if (BUTTON[7])
	  begin
	     DISPLAY <= DISPLAY * 10 + 7;
	  end
	else if (BUTTON[8])
	  begin
	     DISPLAY <= DISPLAY * 10 + 8;
	  end
	else if (BUTTON[9])
	  begin
	     DISPLAY <= DISPLAY * 10 + 9;
	  end
	else
	  begin
	     DISPLAY <= DISPLAY;
	  end
     end // else: !if(STAR)
     end // always@ (posedge CLK)
endmodule // DISPLAY

DDL_Project1/rtl/BUTTON.v
module BUTTON(/*AUTOARG*/
   // Outputs
   O_BUTTON, O_STAR, O_HASH,
   // Inputs
   CLK, STAR, HASH, BUTTON
   );
   input CLK, STAR, HASH;
   input [9:0] BUTTON;
   output [9:0] O_BUTTON;
   output   O_STAR,O_HASH; 

   reg [9:0]   R1, R2;
   reg R3, R4, R5, R6;

   always@ (posedge CLK)
     begin
   R1 <= BUTTON;
   R2 <= R1;
   R3 <= STAR;
   R4 <= R3;
   R5 <= HASH;
   R6 <= R5;
     end

   assign O_BUTTON = ~R2 & R1;
   assign O_STAR = ~R4 & R3;
   assign O_HASH = ~R6 & R5;
endmodule // BUTTON

rtl/TOP.v
module TOP(/*AUTOARG*/
   // Outputs
   RANDOM_BUTTON, DISPLAY, ALERT, UNLOCK,
   // Inputs
   BUTTON, STAR, HASH, CLK, OPEN_BUTTON, CLOSE_SENSOR, RESET
   );
   input [9:0] BUTTON;
   input       STAR; // * (RESET)
   input       HASH; // # (temp_RESET)
   input       CLK, OPEN_BUTTON, CLOSE_SENSOR, RESET;
   output [9:0]   RANDOM_BUTTON;
   output [15:0] DISPLAY;
   output    ALERT, UNLOCK;

   reg       CLOSE = 1'b0;
   reg       PREV_CLOSE_SENSOR = 1'b0;
   reg       OPEN = 1'b0;
   reg       PREV_OPEN_BUTTON = 1'b0;
   reg       ALWAYS_OPEN = 1'b0;
   reg [2:0]    ALWAYS_OPEN_CTRL = 0;
   reg [2:0]    PREV_ALWAYS_OPEN_CTRL;
   
   wire [9:0]    W_BUTTON, O_BUTTON, TEMP_BUTTON;
   wire       W_CORRECT, W_PW_TEMP_RESET, W_ALERT, W_ALERT_OFF, O_STAR, O_HASH;
   wire [15:0]    W_PW, W_PW_TEMP, W_DISPLAY;

   always @ (posedge CLK)
     begin
	if(PREV_ALWAYS_OPEN_CTRL == ALWAYS_OPEN_CTRL)
	  ALWAYS_OPEN_CTRL <= 0;
	if(OPEN_BUTTON == 1 && UNLOCK == 1)
	  begin
      ALWAYS_OPEN_CTRL <= ALWAYS_OPEN_CTRL + 1;
        if(ALWAYS_OPEN_CTRL > 6)
          begin
		        ALWAYS_OPEN <= ~ALWAYS_OPEN;
		        ALWAYS_OPEN_CTRL <= 0;
          end
	  end // if (OPEN_BUTTON == 1)
	PREV_ALWAYS_OPEN_CTRL <= ALWAYS_OPEN_CTRL;
	
	PREV_CLOSE_SENSOR <= CLOSE_SENSOR;
	PREV_OPEN_BUTTON <= OPEN_BUTTON;
	if ((CLOSE_SENSOR == 1'b1) && (PREV_CLOSE_SENSOR == 1'b0))
	  begin
             CLOSE <= ~CLOSE;
             if (OPEN == 1)
               OPEN <= ~OPEN;
             else
               OPEN <= OPEN;
	  end
	else if ((OPEN_BUTTON == 1'b1) && (PREV_OPEN_BUTTON == 1'b0))
	  begin
             OPEN <= ~OPEN;
             if(CLOSE == 1)
               CLOSE <= ~CLOSE;
             else
               CLOSE <= CLOSE;
	  end
	else if ((W_CORRECT == 1'b1) && (CLOSE == 1'b1))
	  begin
             CLOSE <= ~CLOSE;
	  end
	else
	  begin
             OPEN <= OPEN;
             CLOSE <= CLOSE;
	  end
     end // always @ (posedge CLK)

   assign TEMP_BUTTON[9:0] = BUTTON[9:0];
   assign DISPLAY[15:0] = W_DISPLAY[15:0];
   assign UNLOCK = ALWAYS_OPEN||(~CLOSE && (W_CORRECT || OPEN));

   BUTTON 
	BUTTON_INST(
        // Outputs
        .O_BUTTON         (O_BUTTON[9:0]),
        .O_STAR         (O_STAR),
        .O_HASH         (O_HASH),
        // Inputs
        .CLK         (CLK),
        .STAR         (STAR),
        .HASH         (HASH),
        .BUTTON         (TEMP_BUTTON[9:0]));
   
   DISPLAY 
	DISPLAY_INST (
          .BUTTON(O_BUTTON[9:0]),
          .STAR(O_STAR),
          .HASH(O_HASH),
          .CLK(CLK),
          .DISPLAY(W_DISPLAY[15:0])
          );

   RANDOM_NUMBERS 
	RANDOM_NUMBERS_INST (
            .I_NUM(O_BUTTON[9:0]),
            .STAR(O_STAR),
            .O_NUM(RANDOM_BUTTON[9:0])
            );

   COMPARE 
	COMPARE_INST (
          .DISPLAY(W_DISPLAY[15:0]),
          .STAR(O_STAR),
          .CLK(CLK),
          .PW(W_PW[15:0]),
          .PW_TEMP(W_PW_TEMP[15:0]),
          .CORRECT(W_CORRECT),
          .PW_TEMP_RESET(W_PW_TEMP_RESET),
          .ALERT(W_ALERT),
          .ALERT_OFF(W_ALERT_OFF),
          .CLOSE_SENSOR(CLOSE_SENSOR)
          );

   PW_RESET 
	PW_RESET_INST (
      .DISPLAY(W_DISPLAY[15:0]),
      .HASH(O_HASH),
      .STAR(O_STAR),
      .RESET(RESET),
      .CLK(CLK),
      .CORRECT(W_CORRECT),
      .PW_TEMP_RESET(W_PW_TEMP_RESET),
      .PW(W_PW[15:0]),
      .PW_TEMP(W_PW_TEMP[15:0])
      );

   ALERT_COUNTER 
	ALERT_COUNTER_INST (
           .ENABLE(W_ALERT),
           .ALERT(ALERT),
           .CLK(CLK),
           .ALERT_OFF(W_ALERT_OFF)
           );

endmodule // TOP

rtl/TB_TOP.v
`timescale 1ns/1ps

module TB_TOP;
   reg [9:0] BUTTON;
   reg        STAR, CLK, HASH, RESET, OPEN_BUTTON, CLOSE_SENSOR;
   wire [15:0] DISPLAY;
   wire [9:0]  RANDOM_BUTTON;
   wire          ALERT, UNLOCK;

   TOP DUT (
        .BUTTON(BUTTON[9:0]),
        .STAR(STAR),
        .HASH(HASH),
        .CLK(CLK),
        .OPEN_BUTTON(OPEN_BUTTON),
        .RESET(RESET),
        .RANDOM_BUTTON(RANDOM_BUTTON[9:0]),
        .DISPLAY(DISPLAY[15:0]),
        .ALERT(ALERT),
        .UNLOCK(UNLOCK),
        .CLOSE_SENSOR(CLOSE_SENSOR)
        );

   always
     #25
       CLK <= ~CLK;

   initial
     begin
   $dumpfile("result.vcd");
   $dumpvars(0, TB_TOP);
   RESET = 1;
   CLK = 1;
   HASH = 0;
   BUTTON = 0;
   STAR = 0;
   OPEN_BUTTON = 0;
   CLOSE_SENSOR = 0;

   #100
     RESET = 0;
   #100
     STAR = 1;
   #100
     STAR = 0;
   BUTTON[0] = 1;
   #100
     BUTTON[0] = 0;
   #50
     BUTTON[0] = 1;
   #100
     BUTTON[0] = 0;
   #50
     BUTTON[0] = 1;
   #100
     BUTTON[0] = 0;
   #50
     BUTTON[0] = 1;
   #100
     BUTTON[0] = 0;
   STAR = 1;
   #100
     STAR = 0;
   #300
     STAR = 1;
   #100
     STAR = 0;
   BUTTON[9] = 1;
   #100
     BUTTON[9] = 0;
   BUTTON[8] = 1;
   #100
     BUTTON[8] = 0;
   BUTTON[7] = 1;
   #100
     BUTTON[7] = 0;
   BUTTON[6] = 1;
   #100
     BUTTON[6] = 0;
   STAR = 1;
   #100
     STAR = 0;
   #300
     CLOSE_SENSOR = 1;
   #100
     CLOSE_SENSOR = 0;
   #300
     BUTTON[9] = 1;
   #100
     BUTTON[9] = 0;
   BUTTON[8] = 1;
   #100
     BUTTON[8] = 0;
   BUTTON[7] = 1;
   #100
     BUTTON[7] = 0;
   BUTTON[6] = 1;
   #100
     BUTTON[6] = 0;
   STAR = 1;
   #100
     STAR = 0;
   #300
     HASH = 1;
   #100
     HASH = 0;
   BUTTON[1] = 1;
   #100
     BUTTON[1] = 0;
   #50
     BUTTON[1] = 1;
   #100
     BUTTON[1] = 0;
   #50
     BUTTON[1] = 1;
   #100
     BUTTON[1] = 0;
   #50
     BUTTON[1] = 1;
   #100
     BUTTON[1] = 0;
   HASH = 1;
   #100
     HASH = 0;
   #300
     CLOSE_SENSOR = 1;
   #100
     CLOSE_SENSOR = 0;
   #300
     BUTTON[1] = 1;
   #100
     BUTTON[1] = 0;
   #50
     BUTTON[1] = 1;
   #100
     BUTTON[1] = 0;
   #50
     BUTTON[1] = 1;
   #100
     BUTTON[1] = 0;
   #50
     BUTTON[1] = 1;
   #100
     BUTTON[1] = 0;
   STAR = 1;
   #100
     STAR = 0;
   #300
     CLOSE_SENSOR = 1;
   #100
     CLOSE_SENSOR = 0;
   
   #300
     BUTTON[1] = 1;
   #100
     BUTTON[1] = 0;
   #50
     BUTTON[1] = 1;
   #100
     BUTTON[1] = 0;
   #50
     BUTTON[1] = 1;
   #100
     BUTTON[1] = 0;
   #50
     BUTTON[1] = 1;
   #100
     BUTTON[1] = 0;
   STAR = 1;
   #100
     STAR = 0;
   
   #300
     BUTTON[1] = 1;
   #100
     BUTTON[1] = 0;
   #50
     BUTTON[1] = 1;
   #100
     BUTTON[1] = 0;
   #50
     BUTTON[1] = 1;
   #100
     BUTTON[1] = 0;
   #50
     BUTTON[1] = 1;
   #100
     BUTTON[1] = 0;
   #50
     STAR = 1;
   #100
     STAR = 0;
   
   #300
     BUTTON[1] = 1;
   #100
     BUTTON[1] = 0;
   #50
     BUTTON[1] = 1;
   #100
     BUTTON[1] = 0;
   #50
     BUTTON[1] = 1;
   #100
     BUTTON[1] = 0;
   #50
     BUTTON[1] = 1;
   #100
     BUTTON[1] = 0;
   STAR = 1;
   #100
     STAR = 0;

   #300
     BUTTON[1] = 1;
   #100
     BUTTON[1] = 0;
   #50
     BUTTON[1] = 1;
   #100
     BUTTON[1] = 0;
   #50
     BUTTON[1] = 1;
   #100
     BUTTON[1] = 0;
   #50
     BUTTON[1] = 1;
   #100
     BUTTON[1] = 0;
   STAR = 1;
   #100
     STAR = 0;

   #300
     BUTTON[1] = 1;
   #100
     BUTTON[1] = 0;
   #50
     BUTTON[1] = 1;
   #100
     BUTTON[1] = 0;
   #50
     BUTTON[1] = 1;
   #100
     BUTTON[1] = 0;
   #50
     BUTTON[1] = 1;
   #100
     BUTTON[1] = 0;
   #50
     STAR = 1;
   #100
     STAR = 0;   #800
     BUTTON[9] = 1;
   #100
     BUTTON[9] = 0;
   BUTTON[8] = 1;
   #100
     BUTTON[8] = 0;
   BUTTON[7] = 1;
   #100
     BUTTON[7] = 0;
   BUTTON[6] = 1;
   #100
     BUTTON[6] = 0;
   STAR = 1;
   #100
     STAR = 0;
	#200
	  OPEN_BUTTON = 1;
	#400
	  OPEN_BUTTON = 0;
	#500
	  CLOSE_SENSOR = 1;
	#100
	  CLOSE_SENSOR = 0;
	#300
	  OPEN_BUTTON = 1;
	#400
	  OPEN_BUTTON = 0;
	#100
	  CLOSE_SENSOR = 1;
	#100
	  CLOSE_SENSOR = 0;
   #1000
     $finish;
     end // initial begin
endmodule // TB_TOP

DDL_Project1/sim/result.vcd
$date
	Mon Aug  4 21:22:06 2025
$end
$version
	Icarus Verilog
$end
$timescale
	1ps
$end
$scope module TB_TOP $end
$var wire 1 ! UNLOCK $end
$var wire 10 " RANDOM_BUTTON [9:0] $end
$var wire 16 # DISPLAY [15:0] $end
$var wire 1 $ ALERT $end
$var reg 10 % BUTTON [9:0] $end
$var reg 1 & CLK $end
$var reg 1 ' CLOSE_SENSOR $end
$var reg 1 ( HASH $end
$var reg 1 ) OPEN_BUTTON $end
$var reg 1 * RESET $end
$var reg 1 + STAR $end
$scope module DUT $end
$var wire 10 , BUTTON [9:0] $end
$var wire 1 & CLK $end
$var wire 1 ' CLOSE_SENSOR $end
$var wire 16 - DISPLAY [15:0] $end
$var wire 1 ( HASH $end
$var wire 1 ) OPEN_BUTTON $end
$var wire 1 * RESET $end
$var wire 1 + STAR $end
$var wire 10 . TEMP_BUTTON [9:0] $end
$var wire 1 ! UNLOCK $end
$var wire 1 / W_PW_TEMP_RESET $end
$var wire 16 0 W_PW_TEMP [15:0] $end
$var wire 16 1 W_PW [15:0] $end
$var wire 16 2 W_DISPLAY [15:0] $end
$var wire 1 3 W_CORRECT $end
$var wire 1 4 W_ALERT_OFF $end
$var wire 1 5 W_ALERT $end
$var wire 10 6 RANDOM_BUTTON [9:0] $end
$var wire 1 7 O_STAR $end
$var wire 1 8 O_HASH $end
$var wire 10 9 O_BUTTON [9:0] $end
$var wire 1 $ ALERT $end
$var reg 1 : ALWAYS_OPEN $end
$var reg 3 ; ALWAYS_OPEN_CTRL [2:0] $end
$var reg 1 < CLOSE $end
$var reg 1 = OPEN $end
$var reg 3 > PREV_ALWAYS_OPEN_CTRL [2:0] $end
$var reg 1 ? PREV_CLOSE_SENSOR $end
$var reg 1 @ PREV_OPEN_BUTTON $end
$scope module ALERT_COUNTER_INST $end
$var wire 1 & CLK $end
$var wire 1 5 ENABLE $end
$var reg 1 $ ALERT $end
$var reg 1 4 ALERT_OFF $end
$var reg 3 A CNT [2:0] $end
$upscope $end
$scope module BUTTON_INST $end
$var wire 10 B BUTTON [9:0] $end
$var wire 1 & CLK $end
$var wire 1 ( HASH $end
$var wire 10 C O_BUTTON [9:0] $end
$var wire 1 8 O_HASH $end
$var wire 1 7 O_STAR $end
$var wire 1 + STAR $end
$var reg 10 D R1 [9:0] $end
$var reg 10 E R2 [9:0] $end
$var reg 1 F R3 $end
$var reg 1 G R4 $end
$var reg 1 H R5 $end
$var reg 1 I R6 $end
$upscope $end
$scope module COMPARE_INST $end
$var wire 1 4 ALERT_OFF $end
$var wire 1 & CLK $end
$var wire 1 ' CLOSE_SENSOR $end
$var wire 1 7 STAR $end
$var wire 16 J PW_TEMP [15:0] $end
$var wire 16 K PW [15:0] $end
$var wire 16 L DISPLAY [15:0] $end
$var reg 1 5 ALERT $end
$var reg 1 3 CORRECT $end
$var reg 1 / PW_TEMP_RESET $end
$var integer 32 M WRONG [31:0] $end
$upscope $end
$scope module DISPLAY_INST $end
$var wire 10 N BUTTON [9:0] $end
$var wire 1 & CLK $end
$var wire 1 8 HASH $end
$var wire 1 7 STAR $end
$var reg 16 O DISPLAY [15:0] $end
$upscope $end
$scope module PW_RESET_INST $end
$var wire 1 & CLK $end
$var wire 1 3 CORRECT $end
$var wire 16 P DISPLAY [15:0] $end
$var wire 1 8 HASH $end
$var wire 1 / PW_TEMP_RESET $end
$var wire 1 * RESET $end
$var wire 1 7 STAR $end
$var parameter 32 Q INIT $end
$var parameter 32 R PAR_PW $end
$var parameter 32 S PAR_PW_TEMP $end
$var reg 16 T PW [15:0] $end
$var reg 16 U PW_TEMP [15:0] $end
$var reg 3 V STATE [2:0] $end
$upscope $end
$scope module RANDOM_NUMBERS_INST $end
$var wire 10 W I_NUM [9:0] $end
$var wire 10 X O_NUM [9:0] $end
$var wire 1 7 STAR $end
$var wire 10 Y MID_NUM [9:0] $end
$var integer 32 Z a [31:0] $end
$upscope $end
$upscope $end
$upscope $end
$enddefinitions $end
$comment Show the parameter values. $end
$dumpall
b10 S
b1 R
b0 Q
$end
#0
$dumpvars
bx Z
b0 Y
bx X
b0 W
b0 V
bz U
b0 T
bx P
bx O
b0 N
b0 M
bx L
b0 K
bz J
xI
0H
xG
0F
bx E
b0 D
b0 C
b0 B
b0 A
0@
0?
b0 >
0=
0<
b0 ;
0:
b0 9
08
07
bx 6
x5
04
x3
bx 2
b0 1
bz 0
x/
b0 .
bx -
b0 ,
0+
1*
0)
0(
0'
1&
b0 %
0$
bx #
bx "
x!
$end
#25000
0&
#50000
0I
0G
b0 E
1&
#75000
0&
#100000
1&
0*
#125000
0&
#150000
1&
#175000
0&
#200000
b0 "
b0 6
b0 X
b101 Z
17
1F
1&
1+
#225000
0&
#250000
07
b0 #
b0 -
b0 2
b0 L
b0 O
b0 P
1G
1&
#275000
0&
#300000
b1000000000 "
b1000000000 6
b1000000000 X
b10000 Y
b1 9
b1 C
b1 N
b1 W
0F
b1 D
1&
b1 .
b1 B
b1 %
b1 ,
0+
#325000
0&
#350000
b0 "
b0 6
b0 X
b0 Y
b0 9
b0 C
b0 N
b0 W
0G
b1 E
1&
#375000
0&
#400000
b0 D
1&
b0 .
b0 B
b0 %
b0 ,
#425000
0&
#450000
b1000000000 "
b1000000000 6
b1000000000 X
b10000 Y
b1 9
b1 C
b1 N
b1 W
b0 E
b1 D
1&
b1 .
b1 B
b1 %
b1 ,
#475000
0&
#500000
b0 "
b0 6
b0 X
b0 Y
b0 9
b0 C
b0 N
b0 W
b1 E
1&
#525000
0&
#550000
b0 D
1&
b0 .
b0 B
b0 %
b0 ,
#575000
0&
#600000
b1000000000 "
b1000000000 6
b1000000000 X
b10000 Y
b1 9
b1 C
b1 N
b1 W
b0 E
b1 D
1&
b1 .
b1 B
b1 %
b1 ,
#625000
0&
#650000
b0 "
b0 6
b0 X
b0 Y
b0 9
b0 C
b0 N
b0 W
b1 E
1&
#675000
0&
#700000
b0 D
1&
b0 .
b0 B
b0 %
b0 ,
#725000
0&
#750000
b1000000000 "
b1000000000 6
b1000000000 X
b10000 Y
b1 9
b1 C
b1 N
b1 W
b0 E
b1 D
1&
b1 .
b1 B
b1 %
b1 ,
#775000
0&
#800000
b0 "
b0 6
b0 X
b0 Y
b0 9
b0 C
b0 N
b0 W
b1 E
1&
#825000
0&
#850000
b10 Z
17
1F
b0 D
1&
1+
b0 .
b0 B
b0 %
b0 ,
#875000
0&
#900000
1!
07
1G
b0 E
13
1&
#925000
0&
#950000
0F
1&
0+
#975000
0&
#1000000
0G
1&
#1025000
0&
#1050000
1&
#1075000
0&
#1100000
1&
#1125000
0&
#1150000
1&
#1175000
0&
#1200000
1&
#1225000
0&
#1250000
b0 Z
17
1F
1&
1+
#1275000
0&
#1300000
07
1G
1&
#1325000
0&
#1350000
b1000000 "
b1000000 6
b1000000 X
b1000000 Y
b1000000000 9
b1000000000 C
b1000000000 N
b1000000000 W
0F
b1000000000 D
1&
b1000000000 .
b1000000000 B
b1000000000 %
b1000000000 ,
0+
#1375000
0&
#1400000
b0 "
b0 6
b0 X
b0 Y
b0 9
b0 C
b0 N
b0 W
0G
b1000000000 E
b1001 #
b1001 -
b1001 2
b1001 L
b1001 O
b1001 P
1&
#1425000
0&
#1450000
b1000 "
b1000 6
b1000 X
b1000 Y
b100000000 9
b100000000 C
b100000000 N
b100000000 W
b100000000 D
1&
b100000000 .
b100000000 B
b100000000 %
b100000000 ,
#1475000
0&
#1500000
b0 "
b0 6
b0 X
b0 Y
b0 9
b0 C
b0 N
b0 W
b100000000 E
b1100010 #
b1100010 -
b1100010 2
b1100010 L
b1100010 O
b1100010 P
1&
#1525000
0&
#1550000
b10000000 "
b10000000 6
b10000000 X
b10000000 Y
b10000000 9
b10000000 C
b10000000 N
b10000000 W
b10000000 D
1&
b10000000 .
b10000000 B
b10000000 %
b10000000 ,
#1575000
0&
#1600000
b0 "
b0 6
b0 X
b0 Y
b0 9
b0 C
b0 N
b0 W
b10000000 E
b1111011011 #
b1111011011 -
b1111011011 2
b1111011011 L
b1111011011 O
b1111011011 P
1&
#1625000
0&
#1650000
b10 "
b10 6
b10 X
b10 Y
b1000000 9
b1000000 C
b1000000 N
b1000000 W
b1000000 D
1&
b1000000 .
b1000000 B
b1000000 %
b1000000 ,
#1675000
0&
#1700000
b0 "
b0 6
b0 X
b0 Y
b0 9
b0 C
b0 N
b0 W
b1000000 E
b10011010010100 #
b10011010010100 -
b10011010010100 2
b10011010010100 L
b10011010010100 O
b10011010010100 P
1&
#1725000
0&
#1750000
b1 Z
17
1F
b0 D
1&
1+
b0 .
b0 B
b0 %
b0 ,
#1775000
0&
#1800000
07
1G
b0 E
b0 #
b0 -
b0 2
b0 L
b0 O
b0 P
1&
#1825000
0&
#1850000
0F
1&
0+
#1875000
0&
#1900000
0G
1&
#1925000
0&
#1950000
1&
#1975000
0&
#2000000
1&
#2025000
0&
#2050000
1&
#2075000
0&
#2100000
1&
#2125000
0&
#2150000
0!
1<
1?
0/
03
1&
1'
#2175000
0&
#2200000
1&
#2225000
0&
#2250000
0?
1&
0'
#2275000
0&
#2300000
1&
#2325000
0&
#2350000
1&
#2375000
0&
#2400000
1&
#2425000
0&
#2450000
1&
#2475000
0&
#2500000
1&
#2525000
0&
#2550000
b10000000 "
b10000000 6
b10000000 X
b1000000 Y
b1000000000 9
b1000000000 C
b1000000000 N
b1000000000 W
b1000000000 D
1&
b1000000000 .
b1000000000 B
b1000000000 %
b1000000000 ,
#2575000
0&
#2600000
b0 "
b0 6
b0 X
b0 Y
b0 9
b0 C
b0 N
b0 W
b1000000000 E
b1001 #
b1001 -
b1001 2
b1001 L
b1001 O
b1001 P
1&
#2625000
0&
#2650000
b10000 "
b10000 6
b10000 X
b1000 Y
b100000000 9
b100000000 C
b100000000 N
b100000000 W
b100000000 D
1&
b100000000 .
b100000000 B
b100000000 %
b100000000 ,
#2675000
0&
#2700000
b0 "
b0 6
b0 X
b0 Y
b0 9
b0 C
b0 N
b0 W
b100000000 E
b1100010 #
b1100010 -
b1100010 2
b1100010 L
b1100010 O
b1100010 P
1&
#2725000
0&
#2750000
b100000000 "
b100000000 6
b100000000 X
b10000000 Y
b10000000 9
b10000000 C
b10000000 N
b10000000 W
b10000000 D
1&
b10000000 .
b10000000 B
b10000000 %
b10000000 ,
#2775000
0&
#2800000
b0 "
b0 6
b0 X
b0 Y
b0 9
b0 C
b0 N
b0 W
b10000000 E
b1111011011 #
b1111011011 -
b1111011011 2
b1111011011 L
b1111011011 O
b1111011011 P
1&
#2825000
0&
#2850000
b100 "
b100 6
b100 X
b10 Y
b1000000 9
b1000000 C
b1000000 N
b1000000 W
b1000000 D
1&
b1000000 .
b1000000 B
b1000000 %
b1000000 ,
#2875000
0&
#2900000
b0 "
b0 6
b0 X
b0 Y
b0 9
b0 C
b0 N
b0 W
b1000000 E
b10011010010100 #
b10011010010100 -
b10011010010100 2
b10011010010100 L
b10011010010100 O
b10011010010100 P
1&
#2925000
0&
#2950000
b101 Z
17
1F
b0 D
1&
1+
b0 .
b0 B
b0 %
b0 ,
#2975000
0&
#3000000
07
1G
b0 E
b0 #
b0 -
b0 2
b0 L
b0 O
b0 P
b1 M
1&
#3025000
0&
#3050000
0F
1&
0+
#3075000
0&
#3100000
0G
1&
#3125000
0&
#3150000
1&
#3175000
0&
#3200000
1&
#3225000
0&
#3250000
1&
#3275000
0&
#3300000
1&
#3325000
0&
#3350000
18
1H
1&
1(
#3375000
0&
#3400000
08
1I
1&
#3425000
0&
#3450000
b10000 "
b10000 6
b10000 X
b1000000000 Y
b10 9
b10 C
b10 N
b10 W
0H
b10 D
1&
b10 .
b10 B
b10 %
b10 ,
0(
#3475000
0&
#3500000
b0 "
b0 6
b0 X
b0 Y
b0 9
b0 C
b0 N
b0 W
0I
b10 E
b1 #
b1 -
b1 2
b1 L
b1 O
b1 P
1&
#3525000
0&
#3550000
b0 D
1&
b0 .
b0 B
b0 %
b0 ,
#3575000
0&
#3600000
b10000 "
b10000 6
b10000 X
b1000000000 Y
b10 9
b10 C
b10 N
b10 W
b0 E
b10 D
1&
b10 .
b10 B
b10 %
b10 ,
#3625000
0&
#3650000
b0 "
b0 6
b0 X
b0 Y
b0 9
b0 C
b0 N
b0 W
b1011 #
b1011 -
b1011 2
b1011 L
b1011 O
b1011 P
b10 E
1&
#3675000
0&
#3700000
b0 D
1&
b0 .
b0 B
b0 %
b0 ,
#3725000
0&
#3750000
b10000 "
b10000 6
b10000 X
b1000000000 Y
b10 9
b10 C
b10 N
b10 W
b0 E
b10 D
1&
b10 .
b10 B
b10 %
b10 ,
#3775000
0&
#3800000
b0 "
b0 6
b0 X
b0 Y
b0 9
b0 C
b0 N
b0 W
b10 E
b1101111 #
b1101111 -
b1101111 2
b1101111 L
b1101111 O
b1101111 P
1&
#3825000
0&
#3850000
b0 D
1&
b0 .
b0 B
b0 %
b0 ,
#3875000
0&
#3900000
b10000 "
b10000 6
b10000 X
b1000000000 Y
b10 9
b10 C
b10 N
b10 W
b0 E
b10 D
1&
b10 .
b10 B
b10 %
b10 ,
#3925000
0&
#3950000
b0 "
b0 6
b0 X
b0 Y
b0 9
b0 C
b0 N
b0 W
b10001010111 #
b10001010111 -
b10001010111 2
b10001010111 L
b10001010111 O
b10001010111 P
b10 E
1&
#3975000
0&
